{
  "image": "0236_0.95_0.2.jpg",
  "width": 550,
  "height": 413,
  "timing": {
    "dehaze_ms": 62.11190001340583,
    "detect_ms": 31.938000000081956
  },
  "num_detections": 10,
  "detections": [
    {
      "class_id": 2,
      "class_name": "car",
      "confidence": 0.9033769965171814,
      "bbox": [
        0.19594788551330566,
        215.4532470703125,
        165.10296630859375,
        378.42840576171875
      ]
    },
    {
      "class_id": 2,
      "class_name": "car",
      "confidence": 0.8031312823295593,
      "bbox": [
        457.0811462402344,
        179.01397705078125,
        549.9122924804688,
        409.60693359375
      ]
    },
    {
      "class_id": 2,
      "class_name": "car",
      "confidence": 0.7625449895858765,
      "bbox": [
        235.61126708984375,
        206.7533416748047,
        280.0946350097656,
        237.22113037109375
      ]
    },
    {
      "class_id": 2,
      "class_name": "car",
      "confidence": 0.7577974200248718,
      "bbox": [
        95.3183822631836,
        210.01976013183594,
        216.7741241455078,
        254.9168701171875
      ]
    },
    {
      "class_id": 2,
      "class_name": "car",
      "confidence": 0.6518584489822388,
      "bbox": [
        384.0815124511719,
        176.36148071289062,
        547.8013916015625,
        329.2066650390625
      ]
    },
    {
      "class_id": 2,
      "class_name": "car",
      "confidence": 0.6484062671661377,
      "bbox": [
        359.3030090332031,
        204.3637237548828,
        381.1625061035156,
        250.09413146972656
      ]
    },
    {
      "class_id": 2,
      "class_name": "car",
      "confidence": 0.6136398911476135,
      "bbox": [
        170.119140625,
        211.0251922607422,
        257.4700622558594,
        247.24398803710938
      ]
    },
    {
      "class_id": 2,
      "class_name": "car",
      "confidence": 0.5982545018196106,
      "bbox": [
        284.3670349121094,
        204.37783813476562,
        304.9117736816406,
        221.30947875976562
      ]
    },
    {
      "class_id": 2,
      "class_name": "car",
      "confidence": 0.5347326397895813,
      "bbox": [
        340.34759521484375,
        201.3609161376953,
        380.8975830078125,
        238.900146484375
      ]
    },
    {
      "class_id": 2,
      "class_name": "car",
      "confidence": 0.2896401882171631,
      "bbox": [
        378.44110107421875,
        188.3070068359375,
        420.48876953125,
        251.94007873535156
      ]
    }
  ]
}